stack/__init__.py
stack/src/__init__.py
pystack_sherryt400-0.0.2.dist-info/METADATA
pystack_sherryt400-0.0.2.dist-info/WHEEL
pystack_sherryt400-0.0.2.dist-info/top_level.txt
pystack_sherryt400-0.0.2.dist-info/RECORD
