Metadata-Version: 2.1
Name: pystack-sherryt400
Version: 0.0.2
Summary: A synchronized stack data structure for python 3
Home-page: https://github.com/sherryt400/pystack
Author: Sheharyar Naseem
Author-email: sherryfbi1994@gmal.com
License: UNKNOWN
Platform: UNKNOWN
Classifier: Programming Language :: Python :: 3
Classifier: License :: OSI Approved :: MIT License
Classifier: Operating System :: OS Independent
